heroesoflegend/__init__.py
heroesoflegend/heroesoflegend.py
heroesoflegend/rolltables.py
heroesoflegend-0.2.0.dist-info/DESCRIPTION.rst
heroesoflegend-0.2.0.dist-info/METADATA
heroesoflegend-0.2.0.dist-info/RECORD
heroesoflegend-0.2.0.dist-info/WHEEL
heroesoflegend-0.2.0.dist-info/metadata.json
heroesoflegend-0.2.0.dist-info/top_level.txt
