Metadata-Version: 2.0
Name: heroesoflegend
Version: 0.2.0
Summary: Converting Heroes of Legend to a python package
Home-page: https://github.com/venn177/heroesoflegend.py
Author: venn177
Author-email: venn177@gmail.com
License: MIT
Keywords: testing,dnd
Platform: UNKNOWN
